1_RTL/1_TASK/2_SYSTEM_DISIGN/08_SEQUENCE_DETECTOR/sequence_detector.v
`timescale 1ns/1ps

module sequence_detector(
	i_clk	,
	i_rst_n	,
	i_din	,
	o_detect
);

input	i_clk	;
input	i_rst_n	;
input	i_din	;

output	o_detect;

reg [1:0] state	;
reg [1:0] next_state;

parameter S0 = 2'b00;
parameter S1 = 2'b01;
parameter S2 = 2'b10;
parameter S3 = 2'b11;


// State Register
always @(posedge i_clk or negedge i_rst_n) begin
	if(!i_rst_n)
		state <= S0;
	else 
		state <= next_state;
end

// Next State 
always @(*) begin

	case(state)
		// 0
		S0: begin
			if(i_din)
				next_state = S1;
			else
				next_state = S0;
		end
		
		// 1
		S1: begin
			if(i_din)
				next_state = S1;
			else
				next_state = S2;
		end


		// 10
		S2: begin
			if(i_din)
				next_state = S3;
			else
				next_state = S0;
		end

		// 101
		S3: begin
			if(i_din)
				next_state = S1;
			else	
				next_state = S2;
		end

		default: 
			next_state = S0;
	endcase

end

// Mealy Output
assign o_detect = (state == S3) && i_din;

endmodule

1_RTL/1_TASK/2_SYSTEM_DISIGN/08_SEQUENCE_DETECTOR/tb_sequence_detector.v
`timescale 1ns/1ps

module tb_sequence_detector;

reg	i_clk	;
reg	i_rst_n	;
reg	i_din	;

wire	o_detect;

sequence_detector u_sequence_detector (
	.i_clk	 (i_clk	  ),
	.i_rst_n (i_rst_n ),
	.i_din	 (i_din	  ),
	.o_detect(o_detect)
);

initial begin
	i_clk = 1'b0;
	forever #5 i_clk = ~i_clk;
end

initial begin
	i_rst_n = 1'b0;
	i_din	= 1'b0;

	#10 i_rst_n = 1'b1;

	// 1011
	#10 i_din = 1'b1;
	#10 i_din = 1'b0;
	#10 i_din = 1'b1;
	#10 i_din = 1'b1;

	// 000
	#10 i_din = 1'b0;
	#10 i_din = 1'b0;
	#10 i_din = 1'b0;

	// 1011
	#10 i_din = 1'b1;
	#10 i_din = 1'b0;
	#10 i_din = 1'b1;
	#10 i_din = 1'b1;

	#10 $finish;

end

initial begin
	$dumpfile("./sequence_detector.vcd");
	$dumpvars(0, tb_sequence_detector  );
end

initial begin
	$monitor(
		"TIME = %0t | DIN = %b | DETECT = %b",
		$time, i_din, o_detect
	);
end

endmodule

1_RTL/1_TASK/2_SYSTEM_DISIGN/08_SEQUENCE_DETECTOR/sequence_detector.vcd
$date
    Aug 12, 2026  06:44:18
$end
$version
    TOOL:	xmsim(64)	22.03-s012
$end
$timescale
    1 ps
$end

$scope module tb_sequence_detector $end
$var reg       1 !    i_clk $end
$var reg       1 "    i_rst_n $end
$var reg       1 #    i_din $end
$var wire      1 $    o_detect  $end

$scope module u_sequence_detector $end
$var wire      1 %    i_clk  $end
$var wire      1 &    i_rst_n  $end
$var wire      1 '    i_din  $end
$var wire      1 $    o_detect  $end
$var reg       2 (    state [1:0] $end
$var reg       2 )    next_state [1:0] $end
$var parameter  2 *    S0 $end
$var parameter  2 +    S1 $end
$var parameter  2 ,    S2 $end
$var parameter  2 -    S3 $end
$upscope $end

$upscope $end

$enddefinitions $end
$dumpvars
b11 -
b10 ,
b1 +
b0 *
0!
0"
0#
0$
0%
0&
0'
b0 (
b0 )
$end
#5000
1!
1%
#10000
1"
0!
0%
1&
#15000
1!
1%
#20000
1#
0!
0%
1'
b1 )
#25000
1!
1%
b1 (
#30000
0#
0!
0%
0'
b10 )
#35000
1!
1%
b10 (
b0 )
#40000
1#
0!
0%
1'
b11 )
#45000
1!
1%
b11 (
b1 )
1$
#50000
0!
0%
#55000
1!
1%
b1 (
0$
#60000
0#
0!
0%
0'
b10 )
#65000
1!
1%
b10 (
b0 )
#70000
0!
0%
#75000
1!
1%
b0 (
#80000
0!
0%
#85000
1!
1%
#90000
1#
0!
0%
1'
b1 )
#95000
1!
1%
b1 (
#100000
0#
0!
0%
0'
b10 )
#105000
1!
1%
b10 (
b0 )
#110000
1#
0!
0%
1'
b11 )
#115000
1!
1%
b11 (
b1 )
1$
#120000
0!
0%
#125000
1!
1%
b1 (
0$
