1_RTL/1_TASK/2_SYSTEM_DISIGN/09_DEBOUNCER/debouncer.v
`timescale 1ns/1ps

module debouncer (
	i_clk	,
	i_rst_n	,
	i_btn	,
	o_btn
);

input	i_clk	;
input	i_rst_n	;
input	i_btn	;

output 	o_btn	;

reg 	btn_ff1	;
reg 	btn_ff2	;

always @(posedge i_clk or negedge i_rst_n) begin

	if(!i_rst_n) begin
		btn_ff1 <= 1'b0;
		btn_ff2 <= 1'b0;
	end

	else begin
		btn_ff1 <= i_btn;
		btn_ff2 <= btn_ff1;
	end

end

assign o_btn = btn_ff2;

endmodule

1_RTL/1_TASK/2_SYSTEM_DISIGN/09_DEBOUNCER/tb_debouncer.v
`timescale 1ns/1ps

module tb_debouncer;

reg	i_clk	;
reg 	i_rst_n	;
reg 	i_btn	;

wire	o_btn	;

debouncer u_debouncer (
	.i_clk	(i_clk	),
	.i_rst_n(i_rst_n),
	.i_btn	(i_btn	),
	.o_btn	(o_btn	)
);


initial begin
	i_clk = 1'b0;
	forever #5 i_clk = ~i_clk;
end


initial begin

	i_rst_n = 1'b0;
	i_btn	= 1'b0;

	#10 i_rst_n = 1'b1;

	// ON
	#10 i_btn = 1'b1;

	// OFF
	#30 i_btn = 1'b0;

	// ON
	#20 i_btn = 1'b1;

	#30 $finish;

end


initial begin
	$dumpfile("./debouncer.vcd");
	$dumpvars(0, tb_debouncer  );
end


initial begin
	$monitor (
		"TIME = %0t | BTN = %b | OUT = %b",
		$time, i_btn, o_btn
	);
end

endmodule

1_RTL/1_TASK/2_SYSTEM_DISIGN/09_DEBOUNCER/debouncer.vcd
$date
    Aug 12, 2026  07:07:01
$end
$version
    TOOL:	xmsim(64)	22.03-s012
$end
$timescale
    1 ps
$end

$scope module tb_debouncer $end
$var reg       1 !    i_clk $end
$var reg       1 "    i_rst_n $end
$var reg       1 #    i_btn $end
$var wire      1 $    o_btn  $end

$scope module u_debouncer $end
$var wire      1 %    i_clk  $end
$var wire      1 &    i_rst_n  $end
$var wire      1 '    i_btn  $end
$var wire      1 $    o_btn  $end
$var reg       1 (    btn_ff1 $end
$var reg       1 )    btn_ff2 $end
$upscope $end

$upscope $end

$enddefinitions $end
$dumpvars
0!
0"
0#
0$
0%
0&
0'
0(
0)
$end
#5000
1!
1%
#10000
1"
0!
0%
1&
#15000
1!
1%
#20000
1#
0!
0%
1'
#25000
1!
1%
1(
#30000
0!
0%
#35000
1!
1%
1)
1$
#40000
0!
0%
#45000
1!
1%
#50000
0#
0!
0%
0'
#55000
1!
1%
0(
#60000
0!
0%
#65000
1!
1%
0)
0$
#70000
1#
0!
0%
1'
#75000
1!
1%
1(
#80000
0!
0%
#85000
1!
1%
1)
1$
