1_RTL/1_TASK/1_LOGIC_CIRCUIT/11_BCD_TO_7SEG/bcd_to_7seg.v
`timescale 1ns/1ps

module bcd_to_7seg (
	i_bcd,
	o_seg
);

input	[31:0]	i_bcd;

output	[6:0] 	o_seg;

reg 	[6:0]	o_seg;

always @(*) begin

	case (i_bcd[3:0])
	
		4'd0: o_seg = 7'b1111110;
		4'd1: o_seg = 7'b0110000;
		4'd2: o_seg = 7'b1101101;
		4'd3: o_seg = 7'b1111001;
		4'd4: o_seg = 7'b0110011;
		4'd5: o_seg = 7'b1011011;
		4'd6: o_seg = 7'b1011111;
		4'd7: o_seg = 7'b1110000;
		4'd8: o_seg = 7'b1111111;
		4'd9: o_seg = 7'b1111011;

		default: o_seg = 7'b0000000;

	endcase
end

endmodule

1_RTL/1_TASK/1_LOGIC_CIRCUIT/11_BCD_TO_7SEG/tb_bcd_to_7seg.v
`timescale 1ns/1ps

module tb_bcd_to_7seg;

reg	[31:0]	i_bcd;

wire	[6:0]	o_seg;

bcd_to_7seg u_bcd_to_7seg (
	.i_bcd(i_bcd),
	.o_seg(o_seg)
);

initial begin
	i_bcd = 32'd0;

	#10 i_bcd = 32'd1;
	#10 i_bcd = 32'd2;
	#10 i_bcd = 32'd3;
	#10 i_bcd = 32'd4;
	#10 i_bcd = 32'd5;
	#10 i_bcd = 32'd6;
	#10 i_bcd = 32'd7;
	#10 i_bcd = 32'd8;
	#10 i_bcd = 32'd9;

	#10 i_bcd = 32'd10;

	#10 $finish;

end

initial begin
	$dumpfile("./bcd_to_7seg.vcd");
	$dumpvars(0, tb_bcd_to_7seg  );
end

initial begin
	$monitor(
		"TIME = %0t | BCD = %d | SEG = %b ",
		$time, i_bcd, o_seg
	);
end

endmodule

1_RTL/1_TASK/1_LOGIC_CIRCUIT/11_BCD_TO_7SEG/bcd_to_7seg.vcd
$date
    Aug 12, 2026  00:41:58
$end
$version
    TOOL:	xmsim(64)	22.03-s012
$end
$timescale
    1 ps
$end

$scope module tb_bcd_to_7seg $end
$var reg      32 !    i_bcd [31:0] $end
$var wire      7 "    o_seg [6:0] $end

$scope module u_bcd_to_7seg $end
$var wire     32 #    i_bcd [31:0] $end
$var reg       7 $    o_seg [6:0] $end
$upscope $end

$upscope $end

$enddefinitions $end
$dumpvars
b0 !
b1111110 "
b0 #
b1111110 $
$end
#10000
b1 !
b1 #
b110000 $
b110000 "
#20000
b10 !
b10 #
b1101101 $
b1101101 "
#30000
b11 !
b11 #
b1111001 $
b1111001 "
#40000
b100 !
b100 #
b110011 $
b110011 "
#50000
b101 !
b101 #
b1011011 $
b1011011 "
#60000
b110 !
b110 #
b1011111 $
b1011111 "
#70000
b111 !
b111 #
b1110000 $
b1110000 "
#80000
b1000 !
b1000 #
b1111111 $
b1111111 "
#90000
b1001 !
b1001 #
b1111011 $
b1111011 "
#100000
b1010 !
b1010 #
b0 $
b0 "
