1_RTL/5_SEQ_LOGIC/3_FREQ_DIVIDER/fdivider.v
`timescale 1ns/1ps

module fdivider #(
	parameter DIVISOR = 10
)(
	clk_in	,
	rst_n	,
	o_clk_out
);
	input clk_in		;
	input rst_n		;
	output o_clk_out	;

	localparam WIDTH = $clog2(DIVISOR) ;

	reg [WIDTH-1:0] r_count	;

	reg o_clk_out		;
	always @(posedge clk_in or negedge rst_n) begin
		if(~rst_n) begin
			r_count <= 0;
			o_clk_out <= 1'b0;
		end else begin
			if(r_count == DIVISOR -1) begin
				r_count <= 0;
			end else begin
				r_count <= r_count + 1'b1;
			end
	
			if(r_count == (DIVISOR / 2) -1) begin
				o_clk_out <= 1'b1;
			end else if(r_count == DIVISOR -1) begin
				o_clk_out <= 1'b0;
			end
		end
	end
endmodule

1_RTL/5_SEQ_LOGIC/3_FREQ_DIVIDER/tb_fdivider.v
`timescale 1ns/1ps

module tb_fdivider;

reg clk_in	;
reg rst_n	;
wire o_clk_out	;	

fdivider #(
	.DIVISOR(10)
)  uut (
	.clk_in(clk_in)	,
	.rst_n(rst_n)	,
	.o_clk_out(o_clk_out)
);

	always #5 clk_in = ~clk_in;

	initial begin
		clk_in = 0;
		rst_n = 0;
		#20 rst_n = 1;

	repeat(200) @(posedge clk_in);
	$finish;
	
	end

	always @(posedge clk_in) begin
		$display("Time=%0t, clk_in=%b, clk_out=%b", 
		$time,
		clk_in, 
		o_clk_out);
	end

	initial begin
		$dumpfile("./fdivider.vcd");
		$dumpvars(0, uut);
	end

endmodule

1_RTL/5_SEQ_LOGIC/3_FREQ_DIVIDER/fdivider.vcd
$date
    Jul  6, 2026  19:27:02
$end
$version
    TOOL:	xmsim(64)	22.03-s012
$end
$timescale
    1 ps
$end

$scope module tb_fdivider $end

$scope module uut $end
$var parameter 32 !    DIVISOR $end
$var wire      1 "    clk_in  $end
$var wire      1 #    rst_n  $end
$var reg       1 $    o_clk_out $end
$var parameter 32 %    WIDTH $end
$var reg       4 &    r_count [3:0] $end
$upscope $end

$upscope $end

$enddefinitions $end
$dumpvars
b100 %
b1010 !
0"
0#
0$
b0 &
$end
#5000
1"
#10000
0"
#15000
1"
#20000
0"
1#
#25000
1"
b1 &
#30000
0"
#35000
1"
b10 &
#40000
0"
#45000
1"
b11 &
#50000
0"
#55000
1"
b100 &
#60000
0"
#65000
1"
b101 &
1$
#70000
0"
#75000
1"
b110 &
#80000
0"
#85000
1"
b111 &
#90000
0"
#95000
1"
b1000 &
#100000
0"
#105000
1"
b1001 &
#110000
0"
#115000
1"
b0 &
0$
#120000
0"
#125000
1"
b1 &
#130000
0"
#135000
1"
b10 &
#140000
0"
#145000
1"
b11 &
#150000
0"
#155000
1"
b100 &
#160000
0"
#165000
1"
b101 &
1$
#170000
0"
#175000
1"
b110 &
#180000
0"
#185000
1"
b111 &
#190000
0"
#195000
1"
b1000 &
#200000
0"
#205000
1"
b1001 &
#210000
0"
#215000
1"
b0 &
0$
#220000
0"
#225000
1"
b1 &
#230000
0"
#235000
1"
b10 &
#240000
0"
#245000
1"
b11 &
#250000
0"
#255000
1"
b100 &
#260000
0"
#265000
1"
b101 &
1$
#270000
0"
#275000
1"
b110 &
#280000
0"
#285000
1"
b111 &
#290000
0"
#295000
1"
b1000 &
#300000
0"
#305000
1"
b1001 &
#310000
0"
#315000
1"
b0 &
0$
#320000
0"
#325000
1"
b1 &
#330000
0"
#335000
1"
b10 &
#340000
0"
#345000
1"
b11 &
#350000
0"
#355000
1"
b100 &
#360000
0"
#365000
1"
b101 &
1$
#370000
0"
#375000
1"
b110 &
#380000
0"
#385000
1"
b111 &
#390000
0"
#395000
1"
b1000 &
#400000
0"
#405000
1"
b1001 &
#410000
0"
#415000
1"
b0 &
0$
#420000
0"
#425000
1"
b1 &
#430000
0"
#435000
1"
b10 &
#440000
0"
#445000
1"
b11 &
#450000
0"
#455000
1"
b100 &
#460000
0"
#465000
1"
b101 &
1$
#470000
0"
#475000
1"
b110 &
#480000
0"
#485000
1"
b111 &
#490000
0"
#495000
1"
b1000 &
#500000
0"
#505000
1"
b1001 &
#510000
0"
#515000
1"
b0 &
0$
#520000
0"
#525000
1"
b1 &
#530000
0"
#535000
1"
b10 &
#540000
0"
#545000
1"
b11 &
#550000
0"
#555000
1"
b100 &
#560000
0"
#565000
1"
b101 &
1$
#570000
0"
#575000
1"
b110 &
#580000
0"
#585000
1"
b111 &
#590000
0"
#595000
1"
b1000 &
#600000
0"
#605000
1"
b1001 &
#610000
0"
#615000
1"
b0 &
0$
#620000
0"
#625000
1"
b1 &
#630000
0"
#635000
1"
b10 &
#640000
0"
#645000
1"
b11 &
#650000
0"
#655000
1"
b100 &
#660000
0"
#665000
1"
b101 &
1$
#670000
0"
#675000
1"
b110 &
#680000
0"
#685000
1"
b111 &
#690000
0"
#695000
1"
b1000 &
#700000
0"
#705000
1"
b1001 &
#710000
0"
#715000
1"
b0 &
0$
#720000
0"
#725000
1"
b1 &
#730000
0"
#735000
1"
b10 &
#740000
0"
#745000
1"
b11 &
#750000
0"
#755000
1"
b100 &
#760000
0"
#765000
1"
b101 &
1$
#770000
0"
#775000
1"
b110 &
#780000
0"
#785000
1"
b111 &
#790000
0"
#795000
1"
b1000 &
#800000
0"
#805000
1"
b1001 &
#810000
0"
#815000
1"
b0 &
0$
#820000
0"
#825000
1"
b1 &
#830000
0"
#835000
1"
b10 &
#840000
0"
#845000
1"
b11 &
#850000
0"
#855000
1"
b100 &
#860000
0"
#865000
1"
b101 &
1$
#870000
0"
#875000
1"
b110 &
#880000
0"
#885000
1"
b111 &
#890000
0"
#895000
1"
b1000 &
#900000
0"
#905000
1"
b1001 &
#910000
0"
#915000
1"
b0 &
0$
#920000
0"
#925000
1"
b1 &
#930000
0"
#935000
1"
b10 &
#940000
0"
#945000
1"
b11 &
#950000
0"
#955000
1"
b100 &
#960000
0"
#965000
1"
b101 &
1$
#970000
0"
#975000
1"
b110 &
#980000
0"
#985000
1"
b111 &
#990000
0"
#995000
1"
b1000 &
#1000000
0"
#1005000
1"
b1001 &
#1010000
0"
#1015000
1"
b0 &
0$
#1020000
0"
#1025000
1"
b1 &
#1030000
0"
#1035000
1"
b10 &
#1040000
0"
#1045000
1"
b11 &
#1050000
0"
#1055000
1"
b100 &
#1060000
0"
#1065000
1"
b101 &
1$
#1070000
0"
#1075000
1"
b110 &
#1080000
0"
#1085000
1"
b111 &
#1090000
0"
#1095000
1"
b1000 &
#1100000
0"
#1105000
1"
b1001 &
#1110000
0"
#1115000
1"
b0 &
0$
#1120000
0"
#1125000
1"
b1 &
#1130000
0"
#1135000
1"
b10 &
#1140000
0"
#1145000
1"
b11 &
#1150000
0"
#1155000
1"
b100 &
#1160000
0"
#1165000
1"
b101 &
1$
#1170000
0"
#1175000
1"
b110 &
#1180000
0"
#1185000
1"
b111 &
#1190000
0"
#1195000
1"
b1000 &
#1200000
0"
#1205000
1"
b1001 &
#1210000
0"
#1215000
1"
b0 &
0$
#1220000
0"
#1225000
1"
b1 &
#1230000
0"
#1235000
1"
b10 &
#1240000
0"
#1245000
1"
b11 &
#1250000
0"
#1255000
1"
b100 &
#1260000
0"
#1265000
1"
b101 &
1$
#1270000
0"
#1275000
1"
b110 &
#1280000
0"
#1285000
1"
b111 &
#1290000
0"
#1295000
1"
b1000 &
#1300000
0"
#1305000
1"
b1001 &
#1310000
0"
#1315000
1"
b0 &
0$
#1320000
0"
#1325000
1"
b1 &
#1330000
0"
#1335000
1"
b10 &
#1340000
0"
#1345000
1"
b11 &
#1350000
0"
#1355000
1"
b100 &
#1360000
0"
#1365000
1"
b101 &
1$
#1370000
0"
#1375000
1"
b110 &
#1380000
0"
#1385000
1"
b111 &
#1390000
0"
#1395000
1"
b1000 &
#1400000
0"
#1405000
1"
b1001 &
#1410000
0"
#1415000
1"
b0 &
0$
#1420000
0"
#1425000
1"
b1 &
#1430000
0"
#1435000
1"
b10 &
#1440000
0"
#1445000
1"
b11 &
#1450000
0"
#1455000
1"
b100 &
#1460000
0"
#1465000
1"
b101 &
1$
#1470000
0"
#1475000
1"
b110 &
#1480000
0"
#1485000
1"
b111 &
#1490000
0"
#1495000
1"
b1000 &
#1500000
0"
#1505000
1"
b1001 &
#1510000
0"
#1515000
1"
b0 &
0$
#1520000
0"
#1525000
1"
b1 &
#1530000
0"
#1535000
1"
b10 &
#1540000
0"
#1545000
1"
b11 &
#1550000
0"
#1555000
1"
b100 &
#1560000
0"
#1565000
1"
b101 &
1$
#1570000
0"
#1575000
1"
b110 &
#1580000
0"
#1585000
1"
b111 &
#1590000
0"
#1595000
1"
b1000 &
#1600000
0"
#1605000
1"
b1001 &
#1610000
0"
#1615000
1"
b0 &
0$
#1620000
0"
#1625000
1"
b1 &
#1630000
0"
#1635000
1"
b10 &
#1640000
0"
#1645000
1"
b11 &
#1650000
0"
#1655000
1"
b100 &
#1660000
0"
#1665000
1"
b101 &
1$
#1670000
0"
#1675000
1"
b110 &
#1680000
0"
#1685000
1"
b111 &
#1690000
0"
#1695000
1"
b1000 &
#1700000
0"
#1705000
1"
b1001 &
#1710000
0"
#1715000
1"
b0 &
0$
#1720000
0"
#1725000
1"
b1 &
#1730000
0"
#1735000
1"
b10 &
#1740000
0"
#1745000
1"
b11 &
#1750000
0"
#1755000
1"
b100 &
#1760000
0"
#1765000
1"
b101 &
1$
#1770000
0"
#1775000
1"
b110 &
#1780000
0"
#1785000
1"
b111 &
#1790000
0"
#1795000
1"
b1000 &
#1800000
0"
#1805000
1"
b1001 &
#1810000
0"
#1815000
1"
b0 &
0$
#1820000
0"
#1825000
1"
b1 &
#1830000
0"
#1835000
1"
b10 &
#1840000
0"
#1845000
1"
b11 &
#1850000
0"
#1855000
1"
b100 &
#1860000
0"
#1865000
1"
b101 &
1$
#1870000
0"
#1875000
1"
b110 &
#1880000
0"
#1885000
1"
b111 &
#1890000
0"
#1895000
1"
b1000 &
#1900000
0"
#1905000
1"
b1001 &
#1910000
0"
#1915000
1"
b0 &
0$
#1920000
0"
#1925000
1"
b1 &
#1930000
0"
#1935000
1"
b10 &
#1940000
0"
#1945000
1"
b11 &
#1950000
0"
#1955000
1"
b100 &
#1960000
0"
#1965000
1"
b101 &
1$
#1970000
0"
#1975000
1"
b110 &
#1980000
0"
#1985000
1"
b111 &
#1990000
0"
#1995000
1"
b1000 &
#2000000
0"
#2005000
1"
b1001 &
