1_RTL/1_TASK/2_SYSTEM_DISIGN/03_UP_DOWN_COUNTER/up_down_counter.v
`timescale 1ns/1ps

module up_down_counter (
	i_clk		,
	i_rst_n		,
	i_up_down	,
	o_count
);

input	i_clk		;
input 	i_rst_n		;
input 	i_up_down	;

output reg [31:0] o_count;


always @(posedge i_clk or negedge i_rst_n) begin

	if(~i_rst_n) 
		o_count <= 32'd0;

	else if(i_up_down)
		o_count <= o_count + 32'd1;
	
	else
		o_count <= o_count - 32'd1;

end

endmodule

1_RTL/1_TASK/2_SYSTEM_DISIGN/03_UP_DOWN_COUNTER/tb_up_down_counter.v
`timescale 1ns/1ps

module tb_up_down_counter;

reg i_clk	;
reg i_rst_n	;
reg i_up_down	;

wire [31:0] o_count ;

up_down_counter u_up_down_counter (
	.i_clk		(i_clk		),
	.i_rst_n	(i_rst_n	),
	.i_up_down	(i_up_down	),
	.o_count	(o_count	)
);

initial begin
	i_clk 	  = 1'b0;
	i_rst_n	  = 1'b0;
	i_up_down = 1'b0;
	
	#10;
	i_rst_n	  = 1'b1;
	
	// UP
	#40;
	i_up_down = 1'b0;
	
	// DOWN
	#40;
	i_up_down = 1'b1;

	// UP
	#40;

	$finish;
end

always #5 i_clk = ~i_clk;

initial begin
	$dumpfile("./up_down_counter.vcd");
	$dumpvars(0, tb_up_down_counter	 );
end

initial begin
	$monitor(
		"TIME = %0t | CLK = %b | RST_N = %b | UP_DOWN = %b | COUNT = %b",
		$time, i_clk, i_rst_n, i_up_down, o_count
	);
end

endmodule

1_RTL/1_TASK/2_SYSTEM_DISIGN/03_UP_DOWN_COUNTER/up_down_counter.vcd
$date
    Aug 12, 2026  02:49:29
$end
$version
    TOOL:	xmsim(64)	22.03-s012
$end
$timescale
    1 ps
$end

$scope module tb_up_down_counter $end
$var reg       1 !    i_clk $end
$var reg       1 "    i_rst_n $end
$var reg       1 #    i_up_down $end
$var wire     32 $    o_count [31:0] $end

$scope module u_up_down_counter $end
$var wire      1 %    i_clk  $end
$var wire      1 &    i_rst_n  $end
$var wire      1 '    i_up_down  $end
$var reg      32 (    o_count [31:0] $end
$upscope $end

$upscope $end

$enddefinitions $end
$dumpvars
0!
0"
0#
b0 $
0%
0&
0'
b0 (
$end
#5000
1!
1%
#10000
1"
0!
0%
1&
#15000
1!
1%
b11111111111111111111111111111111 (
b11111111111111111111111111111111 $
#20000
0!
0%
#25000
1!
1%
b11111111111111111111111111111110 (
b11111111111111111111111111111110 $
#30000
0!
0%
#35000
1!
1%
b11111111111111111111111111111101 (
b11111111111111111111111111111101 $
#40000
0!
0%
#45000
1!
1%
b11111111111111111111111111111100 (
b11111111111111111111111111111100 $
#50000
0!
0%
#55000
1!
1%
b11111111111111111111111111111011 (
b11111111111111111111111111111011 $
#60000
0!
0%
#65000
1!
1%
b11111111111111111111111111111010 (
b11111111111111111111111111111010 $
#70000
0!
0%
#75000
1!
1%
b11111111111111111111111111111001 (
b11111111111111111111111111111001 $
#80000
0!
0%
#85000
1!
1%
b11111111111111111111111111111000 (
b11111111111111111111111111111000 $
#90000
1#
0!
0%
1'
#95000
1!
1%
b11111111111111111111111111111001 (
b11111111111111111111111111111001 $
#100000
0!
0%
#105000
1!
1%
b11111111111111111111111111111010 (
b11111111111111111111111111111010 $
#110000
0!
0%
#115000
1!
1%
b11111111111111111111111111111011 (
b11111111111111111111111111111011 $
#120000
0!
0%
#125000
1!
1%
b11111111111111111111111111111100 (
b11111111111111111111111111111100 $
