1_RTL/5_SEQ_LOGIC/4_SHIFT_REGISTER/shift_register_sipo.v
`timescale 1ns/1ps

module shift_register_sipo #(
	parameter WIDTH = 32 
)(
	clk		, 
	rst_n		,
	i_serial_in	,
	
	o_parallel_out
);

input clk		;
input rst_n		;
input i_serial_in	;

output reg [WIDTH-1:0]  o_parallel_out;


always @(posedge clk or negedge rst_n) begin
	if(!rst_n)
		o_parallel_out <= {WIDTH{1'b0}};
	else
		o_parallel_out <= {o_parallel_out[WIDTH-2:0], i_serial_in};
end

endmodule

1_RTL/5_SEQ_LOGIC/4_SHIFT_REGISTER/tb_shift_register_sipo.v
`timescale 1ns/1ps

module tb_shift_register_sipo;

localparam WIDTH = 32;

reg clk		;
reg rst_n	;
reg i_serial_in	;

wire [WIDTH-1:0] o_parallel_out;

shift_register_sipo uut(
	.clk(clk)			,
	.rst_n(rst_n)			,
	.i_serial_in(i_serial_in)	,
	.o_parallel_out(o_parallel_out)
);

	initial begin
		clk = 0;
		forever #5 clk = ~clk;
	end

	initial begin
		$dumpfile("./shift_register.vcd");
		$dumpvars(0, uut);
	end

	initial begin
		rst_n = 1'b0; i_serial_in = 0;
		#15 rst_n = 1'b1;
		
		repeat(WIDTH*2) begin
		@(negedge clk);
		i_serial_in = $random % 2;
 		end
	
		#50 $finish;
	end

	initial begin
		$monitor("time=%0t | reset=%b | serial_in=%b | parallel_out=%b", 
		$time, 
		rst_n, 
		i_serial_in, 
		o_parallel_out);

	end
endmodule

1_RTL/5_SEQ_LOGIC/4_SHIFT_REGISTER/shift_register.vcd
$date
    Jul  6, 2026  23:26:55
$end
$version
    TOOL:	xmsim(64)	22.03-s012
$end
$timescale
    1 ps
$end

$scope module tb_shift_register_sipo $end

$scope module uut $end
$var parameter 32 !    WIDTH $end
$var wire      1 "    clk  $end
$var wire      1 #    rst_n  $end
$var wire      1 $    i_serial_in  $end
$var reg      32 %    o_parallel_out [31:0] $end
$upscope $end

$upscope $end

$enddefinitions $end
$dumpvars
b100000 !
0"
0#
0$
b0 %
$end
#5000
1"
#10000
0"
#15000
1"
1#
#20000
0"
#25000
1"
#30000
1$
0"
#35000
1"
b1 %
#40000
0"
#45000
1"
b11 %
#50000
0"
#55000
1"
b111 %
#60000
0"
#65000
1"
b1111 %
#70000
0"
#75000
1"
b11111 %
#80000
0"
#85000
1"
b111111 %
#90000
0$
0"
#95000
1"
b1111110 %
#100000
1$
0"
#105000
1"
b11111101 %
#110000
0"
#115000
1"
b111111011 %
#120000
0$
0"
#125000
1"
b1111110110 %
#130000
1$
0"
#135000
1"
b11111101101 %
#140000
0"
#145000
1"
b111111011011 %
#150000
0$
0"
#155000
1"
b1111110110110 %
#160000
1$
0"
#165000
1"
b11111101101101 %
#170000
0$
0"
#175000
1"
b111111011011010 %
#180000
1$
0"
#185000
1"
b1111110110110101 %
#190000
0$
0"
#195000
1"
b11111101101101010 %
#200000
1$
0"
#205000
1"
b111111011011010101 %
#210000
0"
#215000
1"
b1111110110110101011 %
#220000
0$
0"
#225000
1"
b11111101101101010110 %
#230000
1$
0"
#235000
1"
b111111011011010101101 %
#240000
0$
0"
#245000
1"
b1111110110110101011010 %
#250000
0"
#255000
1"
b11111101101101010110100 %
#260000
0"
#265000
1"
b111111011011010101101000 %
#270000
1$
0"
#275000
1"
b1111110110110101011010001 %
#280000
0$
0"
#285000
1"
b11111101101101010110100010 %
#290000
1$
0"
#295000
1"
b111111011011010101101000101 %
#300000
0"
#305000
1"
b1111110110110101011010001011 %
#310000
0"
#315000
1"
b11111101101101010110100010111 %
#320000
0"
#325000
1"
b111111011011010101101000101111 %
#330000
0$
0"
#335000
1"
b1111110110110101011010001011110 %
#340000
0"
#345000
1"
b11111101101101010110100010111100 %
#350000
0"
#355000
1"
b11111011011010101101000101111000 %
#360000
0"
#365000
1"
b11110110110101011010001011110000 %
#370000
1$
0"
#375000
1"
b11101101101010110100010111100001 %
#380000
0$
0"
#385000
1"
b11011011010101101000101111000010 %
#390000
1$
0"
#395000
1"
b10110110101011010001011110000101 %
#400000
0"
#405000
1"
b1101101010110100010111100001011 %
#410000
0"
#415000
1"
b11011010101101000101111000010111 %
#420000
0"
#425000
1"
b10110101011010001011110000101111 %
#430000
0"
#435000
1"
b1101010110100010111100001011111 %
#440000
0$
0"
#445000
1"
b11010101101000101111000010111110 %
#450000
0"
#455000
1"
b10101011010001011110000101111100 %
#460000
1$
0"
#465000
1"
b1010110100010111100001011111001 %
#470000
0"
#475000
1"
b10101101000101111000010111110011 %
#480000
0"
#485000
1"
b1011010001011110000101111100111 %
#490000
0$
0"
#495000
1"
b10110100010111100001011111001110 %
#500000
0"
#505000
1"
b1101000101111000010111110011100 %
#510000
0"
#515000
1"
b11010001011110000101111100111000 %
#520000
0"
#525000
1"
b10100010111100001011111001110000 %
#530000
0"
#535000
1"
b1000101111000010111110011100000 %
#540000
1$
0"
#545000
1"
b10001011110000101111100111000001 %
#550000
0$
0"
#555000
1"
b10111100001011111001110000010 %
#560000
0"
#565000
1"
b101111000010111110011100000100 %
#570000
1$
0"
#575000
1"
b1011110000101111100111000001001 %
#580000
0"
#585000
1"
b10111100001011111001110000010011 %
#590000
0$
0"
#595000
1"
b1111000010111110011100000100110 %
#600000
0"
#605000
1"
b11110000101111100111000001001100 %
#610000
0"
#615000
1"
b11100001011111001110000010011000 %
#620000
0"
#625000
1"
b11000010111110011100000100110000 %
#630000
0"
#635000
1"
b10000101111100111000001001100000 %
#640000
1$
0"
#645000
1"
b1011111001110000010011000001 %
#650000
0"
#655000
1"
b10111110011100000100110000011 %
#660000
0"
#665000
1"
b101111100111000001001100000111 %
#670000
0"
#675000
1"
b1011111001110000010011000001111 %
#680000
0"
#685000
1"
b10111110011100000100110000011111 %
#690000
0"
#695000
1"
b1111100111000001001100000111111 %
