1_RTL/5_SEQ_LOGIC/5_REGISTER_MAP/simple_register.v
`timescale 1ns/1ps

module simple_register(
	clk	,
	rst_n	,
	i_wdata	,
	i_wen	,

	o_rdata
);

input clk		;
input rst_n		;
input i_wen		;
input [31:0] i_wdata	;

output [31:0] o_rdata;

reg [31:0] r_reg32;

always @(posedge clk or negedge rst_n) begin
	if(rst_n)
		r_reg32 <= 32'h00000000;

	else if(i_wen)
		r_reg32 <= i_wdata;
end

assign o_rdata = r_reg32;
	

endmodule

1_RTL/5_SEQ_LOGIC/5_REGISTER_MAP/tb_simple_register.v
`timescale 1ns/1ps

module tb_simple_register;

reg clk;
reg rst_n;
reg i_wen;
reg [31:0] i_wdata;
wire [31:0] o_rdata;

simple_register uut(
	.clk(clk),
	.rst_n(rst_n),
	.i_wen(i_wen),
	.i_wdata(i_wdata),
	.o_rdata(o_rdata)
);

initial begin
	$dumpfile("./simple_register.vcd");
	$dumpvars(0, uut);
end

initial begin
	clk = 1'b0;
	forever #5 clk = ~clk;
end

initial begin
	$monitor("T=%0t | rst=%b | wdata=%h | rdata=%h",
	$time,
	rst_n,
	i_wen,
	i_wdata,
	o_rdata);
end

initial begin
	rst_n = 1'b0;
	i_wen = 1'b0;
	i_wdata = 32'h00000000;

	#20 rst_n = 1'b1;

	#10 i_wen = 1'b1;
	i_wdata = 32'h12345678;

	#10 i_wen = 1'b0;

	#20 i_wen = 1'b1;
	i_wdata = 32'hABCDEF12;

	#10 i_wen = 1'b0;

	#20 rst_n = 1'b0;

	#20 rst_n = 1'b1;

	#20 $finish;
end

endmodule

1_RTL/5_SEQ_LOGIC/5_REGISTER_MAP/simple_register.vcd
$date
    Jul  6, 2026  21:32:58
$end
$version
    TOOL:	xmsim(64)	22.03-s012
$end
$timescale
    1 ps
$end

$scope module tb_simple_register $end

$scope module uut $end
$var wire      1 !    clk  $end
$var wire      1 "    rst_n  $end
$var wire      1 #    i_wen  $end
$var wire     32 $    i_wdata [31:0] $end
$var wire     32 %    o_rdata [31:0] $end
$var reg      32 &    r_reg32 [31:0] $end
$upscope $end

$upscope $end

$enddefinitions $end
$dumpvars
0!
0"
0#
b0 $
bx %
bx &
$end
#5000
1!
#10000
0!
#15000
1!
#20000
0!
1"
#25000
1!
b0 &
b0 %
#30000
0!
b10010001101000101011001111000 $
1#
#35000
1!
#40000
0!
0#
#45000
1!
#50000
0!
#55000
1!
#60000
0!
b10101011110011011110111100010010 $
1#
#65000
1!
#70000
0!
0#
#75000
1!
#80000
0!
#85000
1!
#90000
0!
0"
#95000
1!
#100000
0!
#105000
1!
#110000
0!
1"
