2_SIM/4_SAMPLE/pipeline.v
`timescale 1ns / 1ps

module pipeline(

input clk,
input rst_n,
input [9:0] in1,
input [9:0] in2,
input [9:0] in3,
input state,
output reg [11:0] out
);

reg [10:0] temp_sum; // 11*bit_reg
reg [9:0] in3_save;

always @(posedge clk or negedge rst_n) begin
    if (!rst_n) begin
        temp_sum <= 11'd0;
        in3_save <= 10'd0;
    end
    else if (!state) begin
            temp_sum <= in1 + in2;
            in3_save <= in3;
        end
    end
always @(posedge clk or negedge rst_n) begin
    if (!rst_n)
        out <= 12'd0;
    else if (!state)
        out <= temp_sum + in3_save;
end
endmodule

2_SIM/4_SAMPLE/tb_pipeline.v
`timescale 1ns/1ps

module tb_pipeline();

reg clk;
reg rst_n;
reg state;
reg [9:0] in1;
reg [9:0] in2;
reg [9:0] in3;

wire [11:0] out;

pipeline uut (
    .clk(clk),
    .rst_n(rst_n),
    .in1(in1),
    .in2(in2),
    .in3(in3),
    .state(state),
    .out(out)
);

always begin
    #5 clk = ~clk;
end

initial begin
    clk = 1'b0;
    rst_n = 1'b0;
    state = 1'b0;

    in1 = 10'd0;
    in2 = 10'd0;
    in3 = 10'd0;

    #10
    rst_n = 1'b0;

    in1 = 10'd10;
    in2 = 10'd20;
    in3 = 10'd30;
   
    #20

    in1 = 10'd100;
    in2 = 10'd200;
    in3 = 10'd300;
   
    #10

    in1 = 10'd1023;
    in2 = 10'd1023;
    in3 = 10'd1023;
   
    #100
    $finish;

end

initial begin
    $dumpfile("./pipeline.vcd");
    $dumpvars(1, uut);
end


endmodule

2_SIM/4_SAMPLE/pipeline.vcd
$date
    Jun 30, 2026  22:30:49
$end
$version
    TOOL:	xmsim(64)	22.03-s012
$end
$timescale
    1 ps
$end

$scope module tb_pipeline $end

$scope module uut $end
$var wire      1 !    clk  $end
$var wire      1 "    rst_n  $end
$var wire     10 #    in1 [9:0] $end
$var wire     10 $    in2 [9:0] $end
$var wire     10 %    in3 [9:0] $end
$var wire      1 &    state  $end
$var reg      12 '    out [11:0] $end
$var reg      11 (    temp_sum [10:0] $end
$var reg      10 )    in3_save [9:0] $end
$upscope $end

$upscope $end

$enddefinitions $end
$dumpvars
0!
0"
b0 #
b0 $
b0 %
0&
b0 '
b0 (
b0 )
$end
#5000
1!
#10000
0!
#15000
1!
#20000
0!
b11110 %
b10100 $
b1010 #
1"
#25000
1!
b11110 (
b11110 )
#30000
0!
#35000
1!
b111100 '
#40000
0!
b100101100 %
b11001000 $
b1100100 #
#45000
1!
b100101100 (
b100101100 )
#50000
0!
#55000
1!
b1001011000 '
#60000
0!
b1111111111 %
b1111111111 $
b1111111111 #
#65000
1!
b11111111110 (
b1111111111 )
#70000
0!
#75000
1!
b101111111101 '
