1_RTL/1_TASK/2_SYSTEM_DISIGN/02_COUNTER/counter.v
`timescale 1ns/1ps

module counter (
	i_clk	,
	i_rst_n	,
	o_count	
);

input	i_clk	;
input	i_rst_n	;

output reg [31:0] o_count;

always @(posedge i_clk or negedge i_rst_n) begin

	if(~i_rst_n) 
		o_count <= 32'd0;

	else
		o_count <= o_count + 32'd1;
	
end

endmodule

1_RTL/1_TASK/2_SYSTEM_DISIGN/02_COUNTER/tb_counter.v
`timescale 1ns/1ps

module tb_counter;

reg	i_clk	;
reg	i_rst_n	;

wire [31:0] o_count;


counter u_counter (
	.i_clk	(i_clk),
	.i_rst_n(i_rst_n),
	.o_count(o_count)
);

initial begin
	i_clk 	= 1'b0;
	i_rst_n = 1'b0;

	#10;
	i_rst_n = 1'b1;
	
	#50;
	i_rst_n = 1'b0;

	#10;
	i_rst_n = 1'b1;

	#50;
	$finish;

end

always #5 i_clk = ~i_clk;

initial begin
	$dumpfile("./counter.vcd");
	$dumpvars(0, tb_counter	 );
end

initial begin
	$monitor(
		"TIME = %0t | CLK = %b | RST_N = %b | COUNT = %h",
		$time, i_clk, i_rst_n, o_count
	);
end

endmodule

1_RTL/1_TASK/2_SYSTEM_DISIGN/02_COUNTER/counter.vcd
$date
    Aug 12, 2026  02:28:21
$end
$version
    TOOL:	xmsim(64)	22.03-s012
$end
$timescale
    1 ps
$end

$scope module tb_counter $end
$var reg       1 !    i_clk $end
$var reg       1 "    i_rst_n $end
$var wire     32 #    o_count [31:0] $end

$scope module u_counter $end
$var wire      1 $    i_clk  $end
$var wire      1 %    i_rst_n  $end
$var reg      32 &    o_count [31:0] $end
$upscope $end

$upscope $end

$enddefinitions $end
$dumpvars
0!
0"
b0 #
0$
0%
b0 &
$end
#5000
1!
1$
#10000
1"
0!
0$
1%
#15000
1!
1$
b1 &
b1 #
#20000
0!
0$
#25000
1!
1$
b10 &
b10 #
#30000
0!
0$
#35000
1!
1$
b11 &
b11 #
#40000
0!
0$
#45000
1!
1$
b100 &
b100 #
#50000
0!
0$
#55000
1!
1$
b101 &
b101 #
#60000
0"
0!
0$
0%
b0 &
b0 #
#65000
1!
1$
#70000
1"
0!
0$
1%
#75000
1!
1$
b1 &
b1 #
#80000
0!
0$
#85000
1!
1$
b10 &
b10 #
#90000
0!
0$
#95000
1!
1$
b11 &
b11 #
#100000
0!
0$
#105000
1!
1$
b100 &
b100 #
#110000
0!
0$
#115000
1!
1$
b101 &
b101 #
