1_RTL/4_COMB_LOGIC/2_ENCODER/interrupt_controller.v
`timescale 1ns/1ps

module interrupt_controller (
	i_int		, 
	i_intAck	,
	o_intId		,
	o_intReq	

);


input [7:0]	i_int		;
input 		i_intAck	;

output [2:0]	o_intId 	;
output 		o_intReq	;

reg [2:0] 	o_intId		;
reg 		o_intReq	;

always @(*) begin
		o_intReq = 1'b0	;
		o_intId	= 3'd0	;

	if (!i_intAck) begin
		case (1'b1)

			i_int[7] : begin
			o_intReq = 1'b1; 
			o_intId = 3'd7;
			end

			i_int[6] : begin
			o_intReq = 1'b1;
			o_intId = 3'd6;
			end

			i_int[5] : begin
			o_intReq = 1'b1;
			o_intId = 3'd5;
			end
	
			i_int[4] : begin
			o_intReq = 1'b1;
			o_intId = 3'd4;
			end

			i_int[3] : begin
			o_intReq = 1'b1;
			o_intId = 3'd3;
			end

			i_int[2] : begin
			o_intReq = 1'b1;
			o_intId = 3'd2;
			end
	
			i_int[1] : begin
			o_intReq = 1'd1;
			o_intId = 3'd1;
			end

			i_int[0] : begin
			o_intReq = 1'b1;
			o_intId = 3'd0;
			end

		endcase
	end
end
			

endmodule

1_RTL/4_COMB_LOGIC/2_ENCODER/tb_interrupt_controller.v
`timescale 1ns/1ps

module tb_interrupt_controller	;

reg [7:0]	i_int		;
reg 		i_intAck	;

wire [2:0] 	o_intId		;
wire 		o_intReq	;


interrupt_controller uut (
	.i_int	 	(i_int		)	,
	.i_intAck	(i_intAck	)	,
	.o_intId	(o_intId	)	,
	.o_intReq	(o_intReq	)	
);

	initial begin
		$dumpfile("./interrupt_controller.vcd");
		$dumpvars(0, uut);
	end

	
	initial begin
		i_int		= 8'b0000_0000	;
		i_intAck	= 1'b0		;
		#10;

		i_int 		= 8'b0000_0001	;
		#10;

		i_int 		= 8'b0000_0010	;
		#10;

		i_int 		= 8'b0000_0100	;
		#10;

		i_int		= 8'b0000_1000	;
		#10;

		i_int		= 8'b0001_0000	;
		#10;

		i_int		= 8'b0010_0000	;
		#10;

		i_int	 	= 8'b0100_0000	;
		#10;

		i_int 		= 8'b1000_0000	;
		#10;

		i_intAck 	= 1'b1		;
		#10;

		i_intAck	= 1'b0		;
		i_int		= 8'b0000_0000	;
		#10;

		$finish;

	end
endmodule

1_RTL/4_COMB_LOGIC/2_ENCODER/interrupt_controller.vcd
$date
    Jul  1, 2026  02:17:54
$end
$version
    TOOL:	xmsim(64)	22.03-s012
$end
$timescale
    1 ps
$end

$scope module tb_interrupt_controller $end

$scope module uut $end
$var wire      8 !    i_int [7:0] $end
$var wire      1 "    i_intAck  $end
$var reg       3 #    o_intId [2:0] $end
$var reg       1 $    o_intReq $end
$upscope $end

$upscope $end

$enddefinitions $end
$dumpvars
b0 !
0"
b0 #
0$
$end
#10000
b1 !
1$
#20000
b10 !
0$
1$
b1 #
#30000
b100 !
0$
b0 #
1$
b10 #
#40000
b1000 !
0$
b0 #
1$
b11 #
#50000
b10000 !
0$
b0 #
1$
b100 #
#60000
b100000 !
0$
b0 #
1$
b101 #
#70000
b1000000 !
0$
b0 #
1$
b110 #
#80000
b10000000 !
0$
b0 #
1$
b111 #
#90000
1"
0$
b0 #
#100000
b0 !
0"
