1_RTL/1_TASK/2_SYSTEM_DISIGN/05_JOHNSON_COUNTER/johnson_counter.v
`timescale 1ns/1ps

module johnson_counter (
	i_clk	,
	i_rst_n	,
	o_count
);

input	i_clk	;
input 	i_rst_n	;

output reg [31:0] o_count ;


always @(posedge i_clk or negedge i_rst_n) begin
	
	if(!i_rst_n)
		o_count <= 32'h0000_0000;
	
	else
		o_count <= {~o_count[31], o_count[31:1]};
end

endmodule

1_RTL/1_TASK/2_SYSTEM_DISIGN/05_JOHNSON_COUNTER/tb_johnson_counter.v
`timescale 1ns/1ps

module tb_johnson_counter;

reg	i_clk	;
reg	i_rst_n	;

wire [31:0] o_count ;


johnson_counter u_johnson_counter (
	.i_clk	(i_clk	),
	.i_rst_n(i_rst_n),
	.o_count(o_count)
);

initial begin
	i_clk 	= 1'b0;
	i_rst_n = 1'b0;

	#10 i_rst_n = 1'b1;

	#350 $finish;

end

always #5 i_clk = ~i_clk;

initial begin
	$dumpfile("./johnson_counter.vcd");
	$dumpvars(0, tb_johnson_counter	 );
end

initial begin
	$monitor (
		"TIME = %0t | CLK = %b | RST_N = %b | COUNT = %h",
		$time, i_clk, i_rst_n, o_count
	);
end

endmodule

1_RTL/1_TASK/2_SYSTEM_DISIGN/05_JOHNSON_COUNTER/johnson_counter.vcd
$date
    Aug 12, 2026  03:06:22
$end
$version
    TOOL:	xmsim(64)	22.03-s012
$end
$timescale
    1 ps
$end

$scope module tb_johnson_counter $end
$var reg       1 !    i_clk $end
$var reg       1 "    i_rst_n $end
$var wire     32 #    o_count [31:0] $end

$scope module u_johnson_counter $end
$var wire      1 $    i_clk  $end
$var wire      1 %    i_rst_n  $end
$var reg      32 &    o_count [31:0] $end
$upscope $end

$upscope $end

$enddefinitions $end
$dumpvars
0!
0"
b0 #
0$
0%
b0 &
$end
#5000
1!
1$
#10000
1"
0!
0$
1%
#15000
1!
1$
b10000000000000000000000000000000 &
b10000000000000000000000000000000 #
#20000
0!
0$
#25000
1!
1$
b1000000000000000000000000000000 &
b1000000000000000000000000000000 #
#30000
0!
0$
#35000
1!
1$
b10100000000000000000000000000000 &
b10100000000000000000000000000000 #
#40000
0!
0$
#45000
1!
1$
b1010000000000000000000000000000 &
b1010000000000000000000000000000 #
#50000
0!
0$
#55000
1!
1$
b10101000000000000000000000000000 &
b10101000000000000000000000000000 #
#60000
0!
0$
#65000
1!
1$
b1010100000000000000000000000000 &
b1010100000000000000000000000000 #
#70000
0!
0$
#75000
1!
1$
b10101010000000000000000000000000 &
b10101010000000000000000000000000 #
#80000
0!
0$
#85000
1!
1$
b1010101000000000000000000000000 &
b1010101000000000000000000000000 #
#90000
0!
0$
#95000
1!
1$
b10101010100000000000000000000000 &
b10101010100000000000000000000000 #
#100000
0!
0$
#105000
1!
1$
b1010101010000000000000000000000 &
b1010101010000000000000000000000 #
#110000
0!
0$
#115000
1!
1$
b10101010101000000000000000000000 &
b10101010101000000000000000000000 #
#120000
0!
0$
#125000
1!
1$
b1010101010100000000000000000000 &
b1010101010100000000000000000000 #
#130000
0!
0$
#135000
1!
1$
b10101010101010000000000000000000 &
b10101010101010000000000000000000 #
#140000
0!
0$
#145000
1!
1$
b1010101010101000000000000000000 &
b1010101010101000000000000000000 #
#150000
0!
0$
#155000
1!
1$
b10101010101010100000000000000000 &
b10101010101010100000000000000000 #
#160000
0!
0$
#165000
1!
1$
b1010101010101010000000000000000 &
b1010101010101010000000000000000 #
#170000
0!
0$
#175000
1!
1$
b10101010101010101000000000000000 &
b10101010101010101000000000000000 #
#180000
0!
0$
#185000
1!
1$
b1010101010101010100000000000000 &
b1010101010101010100000000000000 #
#190000
0!
0$
#195000
1!
1$
b10101010101010101010000000000000 &
b10101010101010101010000000000000 #
#200000
0!
0$
#205000
1!
1$
b1010101010101010101000000000000 &
b1010101010101010101000000000000 #
#210000
0!
0$
#215000
1!
1$
b10101010101010101010100000000000 &
b10101010101010101010100000000000 #
#220000
0!
0$
#225000
1!
1$
b1010101010101010101010000000000 &
b1010101010101010101010000000000 #
#230000
0!
0$
#235000
1!
1$
b10101010101010101010101000000000 &
b10101010101010101010101000000000 #
#240000
0!
0$
#245000
1!
1$
b1010101010101010101010100000000 &
b1010101010101010101010100000000 #
#250000
0!
0$
#255000
1!
1$
b10101010101010101010101010000000 &
b10101010101010101010101010000000 #
#260000
0!
0$
#265000
1!
1$
b1010101010101010101010101000000 &
b1010101010101010101010101000000 #
#270000
0!
0$
#275000
1!
1$
b10101010101010101010101010100000 &
b10101010101010101010101010100000 #
#280000
0!
0$
#285000
1!
1$
b1010101010101010101010101010000 &
b1010101010101010101010101010000 #
#290000
0!
0$
#295000
1!
1$
b10101010101010101010101010101000 &
b10101010101010101010101010101000 #
#300000
0!
0$
#305000
1!
1$
b1010101010101010101010101010100 &
b1010101010101010101010101010100 #
#310000
0!
0$
#315000
1!
1$
b10101010101010101010101010101010 &
b10101010101010101010101010101010 #
#320000
0!
0$
#325000
1!
1$
b1010101010101010101010101010101 &
b1010101010101010101010101010101 #
#330000
0!
0$
#335000
1!
1$
b10101010101010101010101010101010 &
b10101010101010101010101010101010 #
#340000
0!
0$
#345000
1!
1$
b1010101010101010101010101010101 &
b1010101010101010101010101010101 #
#350000
0!
0$
#355000
1!
1$
b10101010101010101010101010101010 &
b10101010101010101010101010101010 #
