1_RTL/5_SEQ_LOGIC/2_REGISTER/register.v
`timescale 1ns/1ps

module register(

	i_rst_n,
	i_clk,

	i_in1,
	i_in2,

	o_out1,
	o_out2

);

input i_rst_n;
input i_clk;

input i_in1;
input [31:0] i_in2;

output reg o_out1;
output reg [31:0] o_out2;

always @(posedge i_clk or negedge i_rst_n) begin

	if(i_rst_n)
		o_out1 <= 1'b0;
	else
		o_out1 <= i_in1;
end

always @(posedge i_clk or negedge i_rst_n) begin

	if(i_rst_n)
		o_out2 <= 32'h00000000;
	else
		o_out2 <= i_in2;
end

endmodule

1_RTL/5_SEQ_LOGIC/2_REGISTER/tb_register.v
`timescale 1ns/1ps

module tb_register;

reg i_rst_n;
reg i_clk;

reg i_in1;
reg [31:0] i_in2;

wire o_out1;
wire [31:0] o_out2;

register uut (
	.i_rst_n(i_rst_n),
	.i_clk(i_clk),
	.i_in1(i_in1),
	.i_in2(i_in2),
	.o_out1(o_out1),
	.o_out2(o_out2)
);

always #5 i_clk = ~i_clk;

initial begin
	$dumpfile("./register.vcd");
	$dumpvars(0, uut);
end

initial begin
	i_rst_n = 1'b0;
	i_clk = 1'b0;
	i_in1 = 1'b0;
	i_in2 = 32'h00000000;

	#20
	i_rst_n = 1'b1;

	#10
	i_in1 = 1'b1;

	#10
	i_in2 = 32'h12345678;

	#20
	i_in1 = 1'b0;
	i_in2 = 32'hAAAAAAAA;

 	#20
	i_rst_n = 1'b0;

	#20
	i_in1 = 1'b1;
	i_in2 = 32'hFFFFFFFF;

	#20
	i_rst_n = 1'b1;

	#20
	i_in2 = 32'h87654321;

	#50
	$finish;
end
endmodule

1_RTL/5_SEQ_LOGIC/2_REGISTER/register.vcd
$date
    Jul  2, 2026  02:06:30
$end
$version
    TOOL:	xmsim(64)	22.03-s012
$end
$timescale
    1 ps
$end

$scope module tb_register $end

$scope module uut $end
$var wire      1 !    i_rst_n  $end
$var wire      1 "    i_clk  $end
$var wire      1 #    i_in1  $end
$var wire     32 $    i_in2 [31:0] $end
$var reg       1 %    o_out1 $end
$var reg      32 &    o_out2 [31:0] $end
$upscope $end

$upscope $end

$enddefinitions $end
$dumpvars
0!
0"
0#
b0 $
0%
b0 &
$end
#5000
1"
#10000
0"
#15000
1"
#20000
0"
1!
#25000
1"
#30000
0"
1#
#35000
1"
#40000
0"
b10010001101000101011001111000 $
#45000
1"
#50000
0"
#55000
1"
#60000
0"
b10101010101010101010101010101010 $
0#
#65000
1"
#70000
0"
#75000
1"
#80000
0"
0!
b10101010101010101010101010101010 &
#85000
1"
#90000
0"
#95000
1"
#100000
0"
b11111111111111111111111111111111 $
1#
#105000
1"
b11111111111111111111111111111111 &
1%
#110000
0"
#115000
1"
#120000
0"
1!
#125000
1"
b0 &
0%
#130000
0"
#135000
1"
#140000
0"
b10000111011001010100001100100001 $
