1_RTL/1_TASK/2_SYSTEM_DISIGN/07_FSM/fsm.v
`timescale 1ns/1ps

module fsm (
	i_clk	,
	i_rst_n	,
	i_din	,
	o_dout
);

input	i_clk	;
input	i_rst_n	;
input	i_din	;

output 	o_dout	;

reg [1:0] state	;
reg [1:0] next_state ; 

parameter S0 = 2'b00;
parameter S1 = 2'b01;
parameter S2 = 2'b10;
parameter S3 = 2'b11;

// State Register
always @(posedge i_clk or negedge i_rst_n) begin
	if(!i_rst_n)
		state <= S0;
	else
		state <= next_state;
end


// Next State Logic
always @(*) begin
	case(state)
		S0: begin
			if(i_din) next_state = S1;
			else	  next_state = S0;
		end

		S1: begin
			if(i_din) next_state = S2;
			else      next_state = S0;
		end

		S2: begin
			if(i_din) next_state = S3;
			else	  next_state = S0;
		end

		S3: begin
			if(i_din) next_state = S3;
			else	  next_state = S0;
		end
	
		default: next_state = S0;
	endcase
end

// Output Logic
assign o_dout = (state == S3);

endmodule

1_RTL/1_TASK/2_SYSTEM_DISIGN/07_FSM/tb_fsm.v
`timescale 1ns/1ps

module tb_fsm;

reg	i_clk	;
reg	i_rst_n	;
reg 	i_din	;

wire	o_dout	;


fsm u_fsm (
	.i_clk	(i_clk	),
	.i_rst_n(i_rst_n),
	.i_din	(i_din	),
	.o_dout	(o_dout	)
);

initial begin
	i_clk = 1'b0;
	forever #5 i_clk = ~i_clk;
end

initial begin

	i_rst_n = 1'b0;
	i_din 	= 1'b0;

	#10 i_rst_n = 1'b1;

	// 0011
	#10 i_din = 1'b0;
	#10 i_din = 1'b0;
	#10 i_din = 1'b0;
	#10 i_din = 1'b1;
	#10 i_din = 1'b1;

	// 0
	#10 i_rst_n = 1'b1;

	// 00111
	#10 i_din = 1'b0;
	#10 i_din = 1'b0;
	#10 i_din = 1'b1;
	#10 i_din = 1'b1;
	#10 i_din = 1'b1;

	// 0 
	#10 i_rst_n = 1'b0;

	// 111
	#10 i_din = 1'b1;
	#10 i_din = 1'b1;
	#10 i_din = 1'b1;

	#10 $finish;
end

initial begin
	$dumpfile("./fsm.vcd"	);
	$dumpvars(0, tb_fsm	);
end

initial begin
	$monitor(
		"TIME = %0t | DIN = %b | DOUT = %b",
		$time, i_din, o_dout
	);
end

endmodule

1_RTL/1_TASK/2_SYSTEM_DISIGN/07_FSM/fsm.vcd
$date
    Aug 12, 2026  06:21:47
$end
$version
    TOOL:	xmsim(64)	22.03-s012
$end
$timescale
    1 ps
$end

$scope module tb_fsm $end
$var reg       1 !    i_clk $end
$var reg       1 "    i_rst_n $end
$var reg       1 #    i_din $end
$var wire      1 $    o_dout  $end

$scope module u_fsm $end
$var wire      1 %    i_clk  $end
$var wire      1 &    i_rst_n  $end
$var wire      1 '    i_din  $end
$var wire      1 $    o_dout  $end
$var reg       2 (    state [1:0] $end
$var reg       2 )    next_state [1:0] $end
$var parameter  2 *    S0 $end
$var parameter  2 +    S1 $end
$var parameter  2 ,    S2 $end
$var parameter  2 -    S3 $end
$upscope $end

$upscope $end

$enddefinitions $end
$dumpvars
b11 -
b10 ,
b1 +
b0 *
0!
0"
0#
0$
0%
0&
0'
b0 (
b0 )
$end
#5000
1!
1%
#10000
1"
0!
0%
1&
#15000
1!
1%
#20000
0!
0%
#25000
1!
1%
#30000
0!
0%
#35000
1!
1%
#40000
0!
0%
#45000
1!
1%
#50000
1#
0!
0%
1'
b1 )
#55000
1!
1%
b1 (
b10 )
#60000
0!
0%
#65000
1!
1%
b10 (
b11 )
#70000
0!
0%
#75000
1!
1%
b11 (
1$
#80000
0#
0!
0%
0'
b0 )
#85000
1!
1%
b0 (
0$
#90000
0!
0%
#95000
1!
1%
#100000
1#
0!
0%
1'
b1 )
#105000
1!
1%
b1 (
b10 )
#110000
0!
0%
#115000
1!
1%
b10 (
b11 )
#120000
0!
0%
#125000
1!
1%
b11 (
1$
#130000
0"
0!
0%
0&
b0 (
b1 )
0$
