1_RTL/1_TASK/2_SYSTEM_DISIGN/01_DFF/dff.v
`timescale 1ns/1ps

module dff (
	i_clk	,
	i_d	,
	o_q
);

input		  i_clk	;
input 	   [31:0] i_d	;

output reg [31:0] o_q	;


always @(posedge i_clk) begin
	o_q <= i_d;
end


endmodule

1_RTL/1_TASK/2_SYSTEM_DISIGN/01_DFF/tb_dff.v
`timescale 1ns/1ps

module tb_dff;

reg 	   	i_clk	;	
reg  [31:0] 	i_d	;

wire [31:0] 	o_q 	;

dff u_dff (
	.i_clk	(i_clk	),
	.i_d	(i_d	),
	.o_q	(o_q	)
);

initial begin
	i_clk = 1'b0;
	i_d   = 32'h0000_0000;

	#10 i_d = 32'h1234_5678;
	#20 i_d = 32'hAAAA_AAAA;
	#20 i_d = 32'hFFFF_0000;
 	#20 i_d = 32'h5555_5555;

	#20 $finish;
end

always #5 i_clk = ~i_clk;

initial begin
	$dumpfile("./dff.vcd"	);
	$dumpvars(0, tb_dff	);
end

initial begin
	$monitor(
		"TIME = %0t | CLK = %b | D = %h | Q = %h",
		$time, i_clk, i_d, o_q
	);
end

endmodule

1_RTL/1_TASK/2_SYSTEM_DISIGN/01_DFF/dff.vcd
$date
    Aug 12, 2026  01:53:55
$end
$version
    TOOL:	xmsim(64)	22.03-s012
$end
$timescale
    1 ps
$end

$scope module tb_dff $end
$var reg       1 !    i_clk $end
$var reg      32 "    i_d [31:0] $end
$var wire     32 #    o_q [31:0] $end

$scope module u_dff $end
$var wire      1 $    i_clk  $end
$var wire     32 %    i_d [31:0] $end
$var reg      32 &    o_q [31:0] $end
$upscope $end

$upscope $end

$enddefinitions $end
$dumpvars
0!
b0 "
bx #
0$
b0 %
bx &
$end
#5000
1!
1$
b0 &
b0 #
#10000
b10010001101000101011001111000 "
0!
0$
b10010001101000101011001111000 %
#15000
1!
1$
b10010001101000101011001111000 &
b10010001101000101011001111000 #
#20000
0!
0$
#25000
1!
1$
#30000
b10101010101010101010101010101010 "
0!
0$
b10101010101010101010101010101010 %
#35000
1!
1$
b10101010101010101010101010101010 &
b10101010101010101010101010101010 #
#40000
0!
0$
#45000
1!
1$
#50000
b11111111111111110000000000000000 "
0!
0$
b11111111111111110000000000000000 %
#55000
1!
1$
b11111111111111110000000000000000 &
b11111111111111110000000000000000 #
#60000
0!
0$
#65000
1!
1$
#70000
b1010101010101010101010101010101 "
0!
0$
b1010101010101010101010101010101 %
#75000
1!
1$
b1010101010101010101010101010101 &
b1010101010101010101010101010101 #
